moleql/__init__.py
moleql/default_casters.py
moleql/mql/__init__.py
moleql/mql/casters.py
moleql/mql/constants.py
moleql/mql/core.py
moleql/mql/date_parser.py
moleql/mql/errors.py
moleql/mql/filter_handler.py
moleql/mql/limit_skip_handler.py
moleql/mql/operator_mapping.py
moleql/mql/projection_handler.py
moleql/mql/regex_parser.py
moleql/mql/sort_handler.py
moleql/mql/text_search_handler.py
moleql/mql/type_mapping.py
moleql/parse.py
moleql/py.typed
moleql-0.1.1.dist-info/WHEEL
moleql-0.1.1.dist-info/METADATA
moleql-0.1.1.dist-info/RECORD
