Metadata-Version: 2.3
Name: moleql
Version: 0.1.1
Summary: Add your description here
Author: Pedro Guzmán
Author-email: Pedro Guzmán <pedro@subvertic.com>
Requires-Dist: dateparse>=1.4.0
Requires-Dist: dateparser>=1.2.2
Requires-Dist: mypy>=1.18.2
Requires-Dist: pymongo>=4.15.3
Requires-Dist: pytest>=8.4.2
Requires-Dist: ruff>=0.14.4
Requires-Python: >=3.12
Project-URL: Homepage, https://github.com/OneTesseractInMultiverse/moleql
Project-URL: Issues, https://github.com/OneTesseractInMultiverse/moleql/issues
